README.rst
setup.py
lookfor/__init__.py
lookfor/lookfor.py
lookfor.egg-info/PKG-INFO
lookfor.egg-info/SOURCES.txt
lookfor.egg-info/dependency_links.txt
lookfor.egg-info/requires.txt
lookfor.egg-info/top_level.txt