Metadata-Version: 1.1
Name: lookfor
Version: 0.0.2
Summary: Search magic extension for IPython
Home-page: https://github.com/jschueller/lookfor
Author: Julien Schueller
Author-email: schueller@phimeca.com
License: BSD
Keywords: search ipython
Platform: UNKNOWN
Classifier: Development Status :: 3 - Alpha
Classifier: Environment :: Web Environment
Classifier: Framework :: IPython
Classifier: Intended Audience :: Science/Research
Classifier: License :: OSI Approved :: BSD License
Classifier: Operating System :: OS Independent
Classifier: Programming Language :: Python
Classifier: Topic :: Software Development :: Libraries :: Python Modules
